asttokens/__init__.py
asttokens/astroid_compat.py
asttokens/asttokens.py
asttokens/line_numbers.py
asttokens/mark_tokens.py
asttokens/py.typed
asttokens/util.py
asttokens/version.py
asttokens-2.4.0.dist-info/LICENSE
asttokens-2.4.0.dist-info/METADATA
asttokens-2.4.0.dist-info/WHEEL
asttokens-2.4.0.dist-info/top_level.txt
asttokens-2.4.0.dist-info/RECORD
